osa/__init__.py
osa/models.py
osa/routes.py
osa/services.py
osa_system-0.1.dist-info/METADATA
osa_system-0.1.dist-info/WHEEL
osa_system-0.1.dist-info/top_level.txt
osa_system-0.1.dist-info/RECORD
