Metadata-Version: 2.1
Name: osa-system
Version: 0.1
Classifier: Programming Language :: Python :: 3
Classifier: Programming Language :: Python :: 3.10
Requires-Dist: flask
Requires-Dist: requests
